evo/__init__.py
evo/main.py
evo/sessions.py
evo/settings.py
evo/usage.py
evo/.claude/settings.local.json
evo_tool-0.1.3.dist-info/METADATA
evo_tool-0.1.3.dist-info/WHEEL
evo_tool-0.1.3.dist-info/entry_points.txt
evo_tool-0.1.3.dist-info/licenses/LICENSE
evo_tool-0.1.3.dist-info/RECORD
