Metadata-Version: 2.4
Name: evo-tool
Version: 0.1.3
Summary: A CLI tool for managing Git worktrees with Claude Code integration
Author-email: Elisey Gusev <elisey.gusev@example.com>
License-Expression: MIT
License-File: LICENSE
Keywords: claude,cli,development,git,worktree
Classifier: Development Status :: 3 - Alpha
Classifier: Environment :: Console
Classifier: Intended Audience :: Developers
Classifier: License :: OSI Approved :: MIT License
Classifier: Operating System :: OS Independent
Classifier: Programming Language :: Python :: 3
Classifier: Programming Language :: Python :: 3.12
Classifier: Topic :: Software Development :: Version Control :: Git
Requires-Python: >=3.12
Requires-Dist: typer>=0.16.0
Provides-Extra: dev
Requires-Dist: pytest-cov>=4.0.0; extra == 'dev'
Requires-Dist: pytest>=8.0.0; extra == 'dev'
Requires-Dist: ruff>=0.8.0; extra == 'dev'
Requires-Dist: ty>=0.0.1a11; extra == 'dev'
